shiftmedia/__init__.py
shiftmedia/backend.py
shiftmedia/exceptions.py
shiftmedia/paths.py
shiftmedia/resizer.py
shiftmedia/storage.py
shiftmedia/utils.py
shiftmedia/version.py
shiftmedia/cli/__init__.py
shiftmedia/cli/cli.py
shiftmedia/cli/colors.py
shiftmedia-0.0.19.dist-info/LICENSE.txt
shiftmedia-0.0.19.dist-info/METADATA
shiftmedia-0.0.19.dist-info/WHEEL
shiftmedia-0.0.19.dist-info/top_level.txt
shiftmedia-0.0.19.dist-info/RECORD
