Metadata-Version: 2.1
Name: shiftmedia
Version: 0.0.19
Summary: External media and file storage for applications
Home-page: https://github.com/projectshift/shift-media
Author: Dmitry Belyakov
Author-email: dmitrybelyakov@gmail.com
License: MIT License
Download-URL: https://github.com/projectshift/shift-media/archive/v0.0.19.tar.gz
Keywords: python3,aws,s3,media,images,video,storage
Platform: UNKNOWN
Classifier: Development Status :: 3 - Alpha
Classifier: License :: OSI Approved :: MIT License
Classifier: Intended Audience :: Developers
Classifier: Intended Audience :: Information Technology
Classifier: Programming Language :: Python :: 3
Classifier: Environment :: Console
Classifier: Environment :: Web Environment
Classifier: Intended Audience :: Developers
Classifier: Topic :: Internet :: WWW/HTTP :: Dynamic Content
Classifier: Topic :: Software Development :: Libraries :: Application Frameworks
Classifier: Topic :: System :: Archiving
Classifier: Topic :: Utilities
Requires-Dist: Pillow (<9.0.0,>=8.2.0)
Requires-Dist: boto3 (<2.0,>=1.17.78)
Requires-Dist: click (<9.0.0,>=8.0.0)
Requires-Dist: python-magic (<1.0.0,>=0.4.22)
Requires-Dist: piexif (<2,>=1.1.3)
